.bumpversion.cfg
.dockerignore
.gitignore
CHANGELOG.md
Dockerfile
MANIFEST.in
README.md
completer.hist
justfile
requirements-dev.txt
requirements-flake8.txt
requirements.txt
setup.py
template-version.txt
tox.ini
.githooks/prepare-commit-msg
Examples/loop.tasks
src/fhs_iptv_tools/__init__.py
src/fhs_iptv_tools/__version__.py
src/fhs_iptv_tools/cli.py
src/fhs_iptv_tools/config.py
src/fhs_iptv_tools/directories.py
src/fhs_iptv_tools/fhs_iptv_tools.py
src/fhs_iptv_tools/import_m3u.py
src/fhs_iptv_tools/interactive_cmd2.py
src/fhs_iptv_tools/playyaml.py
src/fhs_iptv_tools/playyaml_lib.py
src/fhs_iptv_tools/probe.py
src/fhs_iptv_tools/probe_list.py
src/fhs_iptv_tools/subgroup.py
src/fhs_iptv_tools/utils.py
src/fhs_iptv_tools.egg-info/PKG-INFO
src/fhs_iptv_tools.egg-info/SOURCES.txt
src/fhs_iptv_tools.egg-info/dependency_links.txt
src/fhs_iptv_tools.egg-info/entry_points.txt
src/fhs_iptv_tools.egg-info/requires.txt
src/fhs_iptv_tools.egg-info/top_level.txt
tests/test_sample.py