Metadata-Version: 2.1
Name: fhs-iptv-tools
Version: 0.8.13
Summary: foxhunt software iptv tools, making iptv easier
Home-page: https://github.com/foxhunt72/fhs-iptv-tools
Author: Richard de Vos
Author-email: rdevos72@gmail.com
License: MIT license
Classifier: Development Status :: 4 - Beta
Classifier: Programming Language :: Python
Classifier: Programming Language :: Python :: 3
Classifier: Programming Language :: Python :: 3.6
Classifier: Programming Language :: Python :: 3.7
Classifier: Programming Language :: Python :: 3.8
Classifier: Programming Language :: Python :: 3.9
Classifier: Programming Language :: Python :: 3.10
Requires-Dist: typer[all]
Requires-Dist: cmd2
Requires-Dist: jinja2
Requires-Dist: appdirs
Requires-Dist: pyyaml
Requires-Dist: pyxtream
Requires-Dist: requests
